MANIFEST.in
README.md
setup.cfg
setup.py
bin/elem
elem/__init__.py
elem/cve_test.py
elem/elem.py
elem/elem_configuration.py
elem/log.py
elem.egg-info/PKG-INFO
elem.egg-info/SOURCES.txt
elem.egg-info/dependency_links.txt
elem.egg-info/requires.txt
elem.egg-info/top_level.txt
elem/config/elem.conf
elem/core/__init__.py
elem/core/elem_resource.py
elem/core/elem_resource_cache.py
elem/core/elem_resource_connector.py
elem/core/util.py
elem/exploit/__init__.py
elem/exploit/curated_exploit.py
elem/exploit/curation_manager.py
elem/exploit/exploit_source.py
elem/host/__init__.py
elem/host/assessor.py
elem/host/patcher.py
elem/score/__init__.py
elem/score/score.py
elem/score/score_manager.py
elem/vulnerability/__init__.py
elem/vulnerability/security_api_source.py
elem/vulnerability/vulnerability_manager.py
elem/vulnerability/vulnerability_source.py