Metadata-Version: 1.1
Name: elem
Version: 0.2.3
Summary: Tool to correlate published CVE's against Enterprise Linux against known exploits.
Home-page: https://github.com/fedoraredteam/elem
Author: Kenneth Evensen
Author-email: kevensen@redhat.com
License: GPLv3
Download-URL: https://github.com/fedoraredteam/elem/archive/0.2.2.tar.gz
Keywords: cve,exploit,linux
Platform: Linux
Classifier: Development Status :: 4 - Beta
Classifier: License :: OSI Approved :: GNU General Public License v3 (GPLv3)
Classifier: Programming Language :: Python :: 2.7
